continuousbeam/__init__.py
continuousbeam/analysis.py
continuousbeam/beam_data.py
continuousbeam/contibeam_main.py
continuousbeam/load_data.py
continuousbeam/MyIcons/__init__.py
continuousbeam/MyIcons/anticlockwise-moment.gif
continuousbeam/MyIcons/clockwise-moment.gif
continuousbeam/MyIcons/down-arrow.gif
continuousbeam/MyIcons/up-arrow.gif
continuousbeam/MyIcons/__pycache__/__init__.cpython-38.pyc
continuousbeam/__pycache__/__init__.cpython-38.pyc
continuousbeam/__pycache__/analysis.cpython-38.pyc
continuousbeam/__pycache__/beam_data.cpython-38.pyc
continuousbeam/__pycache__/contibeam_main.cpython-38.pyc
continuousbeam/__pycache__/load_data.cpython-38.pyc
continuousbeam-2023.11.0.dist-info/LICENSE
continuousbeam-2023.11.0.dist-info/METADATA
continuousbeam-2023.11.0.dist-info/WHEEL
continuousbeam-2023.11.0.dist-info/entry_points.txt
continuousbeam-2023.11.0.dist-info/top_level.txt
continuousbeam-2023.11.0.dist-info/RECORD
